data/animals.csv
data/jumpers.csv
data/manual_vehicles.csv
data/metals.csv
data/names.csv
data/vehicles.csv
problem_bank_helpers/__init__.py
problem_bank_helpers/data/animals.csv
problem_bank_helpers/data/jumpers.csv
problem_bank_helpers/data/manual_vehicles.csv
problem_bank_helpers/data/metals.csv
problem_bank_helpers/data/names.csv
problem_bank_helpers/data/vehicles.csv
problem_bank_helpers/problem_bank_helpers.py
problem_bank_helpers/stats.py
problem_bank_helpers-0.3.2.dist-info/LICENSE
problem_bank_helpers-0.3.2.dist-info/METADATA
problem_bank_helpers-0.3.2.dist-info/WHEEL
problem_bank_helpers-0.3.2.dist-info/RECORD
