Metadata-Version: 2.1
Name: problem_bank_helpers
Version: 0.3.2
Summary: Helpful utilities for the open problem bank.
Home-page: https://github.com/open-resources/problem_bank_helpers
License: MIT
Author: Firas Moosvi and Jake Bobowski
Requires-Python: >=3.10
Classifier: License :: OSI Approved :: MIT License
Classifier: Programming Language :: Python :: 3
Classifier: Programming Language :: Python :: 3.10
Classifier: Programming Language :: Python :: 3.11
Classifier: Programming Language :: Python :: 3.12
Requires-Dist: matplotlib (>=3.9.2,<4.0.0)
Requires-Dist: numpy (>=1.26.4,<2.0.0)
Requires-Dist: pandas (>=2.2.2,<3.0.0)
Requires-Dist: scipy (>=1.14.0,<2.0.0)
Requires-Dist: sigfig (>=1.3.3,<2.0.0)
Project-URL: Documentation, https://problem_bank_helpers.readthedocs.io/en/latest/
Project-URL: Repository, https://github.com/open-resources/problem_bank_helpers
